README
ffmigration
ffmigration.py
setup.py
ffmigration.egg-info/PKG-INFO
ffmigration.egg-info/SOURCES.txt
ffmigration.egg-info/dependency_links.txt
ffmigration.egg-info/top_level.txt