Metadata-Version: 1.0
Name: ffmigration
Version: 0.4
Summary: Simple Forward-only database migrations
Home-page: http://www.pegueroles.com/
Author: Ferran Pegueroles Forcadell
Author-email: ferran@pegueroles.com
License: GPL
Download-URL: https://bitbucket.org/ferranp/ffmigration/downloads
Platform: linux
Platform: windows
Classifier: Development Status :: 5 - Production/Stable
Classifier: Environment :: Console
Classifier: Intended Audience :: End Users/Desktop
Classifier: Intended Audience :: Information Technology
Classifier: Intended Audience :: System Administrators
Classifier: License :: OSI Approved :: GNU General Public License (GPL)
Classifier: Programming Language :: Python
Classifier: Topic :: Database
Classifier: Topic :: Utilities
